Workbook

Sheet Corpus
A1: ID | B1: Title | C1: Authors | D1: Year | E1: Venue | F1: Type | G1: Publisher / Index | H1: Found via | I1: Relevance | J1: Technique / role | K1: Link | L1: Notes
A2: 1 | B2: CertiQ: contract-based verification of a realistic quantum compiler | C2: Shi, Li, Tao, Javadi-Abhari, Cross, Chong, Gu | D2: 2019 | E2: arXiv (cs.PL/quant-ph) | F2: Preprint | G2: arXiv | H2: GS p1/p3 | I2: Yes | J2: Compiler verification (C7) | K2: arxiv.org/abs/1908.08963 | L2: Verifies Qiskit passes; finds 3 bugs
A3: 2 | B3: QDiff: Differential testing of quantum software stacks | C3: Wang, Zhang, Xu, Kim | D3: 2021 | E3: ASE | F3: Conference | G3: IEEE Xplore | H3: GS p1 | I3: Yes | J3: Differential testing (C2) | K3: ieeexplore.ieee.org | L3: Cross-stack differential oracle
A4: 3 | B4: Giallar: Push-button verification for the Qiskit quantum compiler | C4: Tao, Shi, Yao, Li, Javadi-Abhari, Cross, Chong, Gu | D4: 2022 | E4: PLDI | F4: Conference | G4: ACM DL | H4: GS p1 | I4: Yes | J4: Compiler verification (C7) | K4: dl.acm.org | L4: Verified 44/56 passes
A5: 4 | B5: MorphQ: Metamorphic testing of the Qiskit quantum computing platform | C5: Paltenghi, Pradel | D5: 2023 | E5: ICSE | F5: Conference | G5: IEEE Xplore | H5: Verified (refs) | I5: Yes | J5: Metamorphic (C3) | K5: arxiv.org/abs/2206.01111 | L5: 13 bugs; ICSE co-listed ACM DL
A6: 5 | B6: MorphQ++: A reproducibility study of metamorphic testing on quantum compilers | C6: Kitt et al. | D6: 2024 | E6: ASE Workshops | F6: Workshop | G6: IEEE Xplore | H6: Verified (refs) | I6: Yes | J6: Metamorphic (C3) | L6: Co-listed ACM DL
A7: 6 | B7: QEMI: A quantum software stacks testing framework via equivalence modulo inputs | C7: Luo, Xia, Zhang, Zhao | D7: 2026 | E7: FASE | F7: Conference | G7: SpringerLink | H7: Verified (refs) | I7: Yes | J7: Equivalence modulo inputs (C4) | K7: arxiv.org/abs/2602.09942 | L7: EMI adapted to quantum
A8: 7 | B8: QuCheck: A property-based testing framework for quantum programs in Qiskit | C8: Pontolillo et al. | D8: 2025 | E8: arXiv | F8: Preprint | G8: arXiv | H8: Verified (refs) | I8: Yes | J8: Property-based (C5) | K8: arxiv.org/abs/2503.22641
A9: 8 | B9: QuteFuzz: Fuzzing quantum compilers using randomly generated circuits | C9: Iwumbwe, Liu, Wickerson | D9: 2025 | E9: PLanQC (POPL workshop) | F9: Workshop | G9: ACM DL | H9: Verified (refs) | I9: Yes | J9: Random generation / fuzzing (C1) | L9: 17 bugs across Qiskit/Cirq/Pytket
A10: 9 | B10: QSPE: Enumerating skeletal quantum programs for quantum library testing | C10: Ye et al. | D10: 2026 | E10: arXiv | F10: Preprint | G10: arXiv | H10: Verified (refs) | I10: Yes | J10: Differential testing (C2) | K10: arxiv.org/abs/2602.00024
A11: 10 | B11: Benchmarking the performance of quantum computing software (Benchpress) | C11: Nation, Saki, Brandhofer et al. | D11: 2025 | E11: Nature Computational Science | F11: Journal | G11: Springer Nature (Nature) | H11: Verified (refs) | I11: Yes | J11: Benchmark (RQ4) | L11: Performance benchmarking suite
A12: 11 | B12: Bugs4Q: A benchmark of existing bugs for controlled testing of quantum programs | C12: Zhao, Zhao, Miao, Lan | D12: 2023 | E12: Journal of Systems and Software | F12: Journal | G12: ScienceDirect (Elsevier) | H12: Verified (refs) | I12: Yes | J12: Bug benchmark (RQ4) | L12: Also ASE 2021 short version
A13: 12 | B13: Advanced equivalence checking for quantum circuits | C13: Burgholzer, Wille | D13: 2021 | E13: IEEE TCAD | F13: Journal | G13: IEEE Xplore | H13: Verified (refs) | I13: Yes | J13: Equivalence checking (C6) | L13: Translation-validation lineage
A14: 13 | B14: Verifying results of the IBM Qiskit quantum circuit compilation flow | C14: Burgholzer, Raymond, Wille | D14: 2020 | E14: IEEE QCE | F14: Conference | G14: IEEE Xplore | H14: Verified (refs) | I14: Yes | J14: Equivalence checking (C6)
A15: 14 | B15: Equivalence checking of quantum circuits via path-sum and weighted model counting | C15: Mei et al. | D15: 2026 | E15: TACAS | F15: Conference | G15: SpringerLink | H15: Verified (refs) | I15: Yes | J15: Equivalence checking (C6)
A16: 15 | B16: Concolic testing for quantum compilers | C16: Choudhury, Bhave, Basu | D16: 2025 | E16: IEEE ICCD | F16: Conference | G16: IEEE Xplore | H16: GS p1 | I16: Yes | J16: Concolic / symbolic (C1) | K16: ieeexplore.ieee.org | L16: Finds missed optimisations
A17: 16 | B17: Statistical testing of quantum programs via fixed-point amplitude amplification | C17: Kang, Lee, Oh | D17: 2024 | E17: OOPSLA | F17: Conference | G17: ACM DL | H17: Verified (refs) | I17: Yes | J17: Statistical oracle (RQ2) | L17: Repeated-measurement oracle
A18: 17 | B18: Exact inference for quantum circuits: a testing oracle for quantum software stacks | C18: Lee, Hong, Ryu | D18: 2025 | E18: ASE | F18: Conference | G18: IEEE Xplore | H18: Verified (refs) | I18: Yes | J18: Testing oracle (RQ2) | L18: Co-listed ACM DL
A19: 18 | B19: Bugs in quantum computing platforms: an empirical study | C19: Paltenghi, Pradel | D19: 2022 | E19: OOPSLA | F19: Conference | G19: ACM DL | H19: GS p1 | I19: Yes | J19: Empirical bug study (RQ1) | K19: dl.acm.org | L19: 39.9% quantum-specific bugs
A20: 19 | B20: A survey on testing and analysis of quantum software | C20: Paltenghi, Pradel | D20: 2024 | E20: arXiv | F20: Preprint (survey) | G20: arXiv | H20: GS p1 | I20: Yes (secondary) | J20: Survey | K20: arxiv.org/abs/2410.00650 | L20: Broad QS testing survey
A21: 20 | B21: A survey on fuzz testing for quantum computing | C21: Betanzo | D21: 2025 | E21: IEEE CHILECON | F21: Conference | G21: IEEE Xplore | H21: GS p2 | I21: Yes (secondary) | J21: Survey / fuzzing | K21: ieeexplore.ieee.org
A22: 21 | B22: An experience-based classification of quantum bugs in quantum software | C22: Quetschlich, Di Matteo | D22: 2025 | E22: Computing (Springer) | F22: Journal | G22: SpringerLink | H22: GS p2 | I22: Maybe | J22: Bug taxonomy | L22: Quantum bugs, not compiler-specific
A23: 22 | B23: IterTestQ: Assembly-level, cross-platform testing of quantum computing platforms | C23: Paltenghi, Pradel | D23: 2026 | E23: Preprint (venue TBD) | F23: Preprint | G23: arXiv | H23: GS p3 | I23: Yes | J23: Differential testing (C2) | K23: software-lab.org | L23: Newer than survey
A24: 23 | B24: Muskit: A mutation analysis tool for quantum software testing | C24: Mendiluze, Ali, Yue, Arcaini | D24: 2021 | E24: ASE | F24: Conference | G24: IEEE Xplore | H24: Verified (refs) | I24: Yes | J24: Mutation testing | L24: Co-listed ACM DL
A25: 24 | B25: QMutPy / Mutation testing of quantum programs: a case study with Qiskit | C25: Fortunato, Campos, Abreu | D25: 2022 | E25: IEEE TQE | F25: Journal | G25: IEEE Xplore | H25: Verified (refs) | I25: Yes | J25: Mutation testing
A26: 25 | B26: A verified optimizer for quantum circuits (VOQC) | C26: Hietala, Rand, Hung, Wu, Hicks | D26: 2021 | E26: POPL | F26: Conference | G26: ACM DL | H26: Verified (refs) | I26: Yes | J26: Compiler verification (C7) | L26: Coq-verified optimiser
A27: 26 | B27: Verified compilation of quantum oracles | C27: Li, Voichick, Hietala, Peng, Wu et al. | D27: 2022 | E27: OOPSLA | F27: Conference | G27: ACM DL | H27: GS p1 | I27: Maybe | J27: Compiler verification (C7) | K27: dl.acm.org | L27: 'oracle' = algorithmic, borderline
A28: 27 | B28: Automating the comparison of quantum compilers for quantum circuits | C28: Salm, Barzen, Leymann, Weder | D28: 2021 | E28: Springer symposium | F28: Conference | G28: SpringerLink | H28: GS p3 | I28: Maybe | J28: Compiler evaluation | L28: Evaluation infrastructure
A29: 28 | B29: Quamap: A multi-backend benchmark dataset for quantum circuit mapping | C29: Zhao, Li, Yin | D29: 2026 | E29: ACM SIGKDD | F29: Conference | G29: ACM DL | H29: GS p1 | I29: Maybe | J29: Benchmark / mapping (RQ4) | K29: dl.acm.org
A30: 29 | B30: Projection-based runtime assertions for testing and debugging quantum programs | C30: Li, Zhou, Yu, Ding, Ying, Xie | D30: 2020 | E30: OOPSLA (PACMPL) | F30: Conference | G30: ACM DL | H30: GS p4 | I30: Yes (secondary) | J30: Runtime assertion oracle (RQ2) | K30: dl.acm.org | L30: 175 citations; assertion-based oracle for QP testing
A31: 30 | B31: Shaking up quantum simulators with fuzzing and rigour | C31: Klimis, Bensoussan, Chachkarova et al. | D31: 2025 | E31: ACM (proceedings; exact venue truncated in listing) | F31: Conference | G31: ACM DL | H31: GS p4 | I31: Yes (secondary) | J31: Fuzzing + differential testing | K31: dl.acm.org | L31: Targets simulators, not compiler; confirm venue on full text
A32: 31 | B32: QuraTest: Integrating quantum specific features in quantum program testing | C32: Ye, Xia, Zhang, Arcaini, Ma et al. | D32: 2023 | E32: ASE | F32: Conference | G32: IEEE Xplore | H32: GS p4 | I32: Yes | J32: Quantum program testing framework (RQ1) | K32: ieeexplore.ieee.org | L32: Co-listed ACM DL
A33: 32 | B33: Arline benchmarks: Automated benchmarking platform for quantum compilers | C33: Kharkov, Ivanova, Mikhantiev et al. | D33: 2022 | E33: arXiv | F33: Preprint | G33: arXiv | H33: GS p5 | I33: Yes (secondary) | J33: Benchmark (RQ4) | K33: arxiv.org | L33: Compares compiler-framework performance
A34: 33 | B34: A Mutation-Based Framework for Efficiency Evaluation of Quantum Compilers | C34: Jiang, Yang, Liu, Deng, Huang | D34: 2025 | E34: SSRN working paper | F34: Preprint | G34: SSRN | H34: GS p5 | I34: Yes | J34: Mutation testing / compiler evaluation | K34: papers.ssrn.com | L34: Year approximate (SSRN id 6997092); tests SABRE/QMAP/FiDLS
A35: 34 | B35: Quantum software engineering: Landscapes and horizons | C35: Zhao | D35: 2020 | E35: arXiv | F35: Preprint (survey) | G35: arXiv | H35: GS p7 | I35: Maybe | J35: Survey / landscape (background) | K35: arxiv.org | L35: 314 citations; broad QSE survey incl. bug patterns
A36: 35 | B36: Quantum Mutant Equivalence via Transpilation | C36: Campos, Miranskyy | D36: 2026 | E36: arXiv | F36: Preprint | G36: arXiv | H36: GS eq-check | I36: Yes | J36: Mutation + equivalence via transpilation (C2/C4) | K36: arxiv.org | L36: Uses transpilation itself as an equivalence oracle
A37: 36 | B37: QuaSi: A scalable and reliable quantum simulation-based equivalence checking framework | C37: Lu, Choudhury, Basu | D37: 2024 | E37: IEEE Conf. on Quantum Computing & Engineering (venue truncated) | F37: Conference | G37: IEEE Xplore | H37: GS eq-check | I37: Yes | J37: Equivalence checking (C6) | K37: ieeexplore.ieee.org | L37: Verifies transpilation correctness
A38: 37 | B38: Practical verification of quantum circuit transformations | C38: Ricciardi | D38: 2026 | E38: PhD thesis, HAL | F38: Thesis | G38: Other | H38: GS eq-check | I38: Yes | J38: Compiler-transformation verification (C6/C7) | K38: theses.hal.science
A39: 38 | B39: Scalable Compilation and Equivalence Checking of Quantum Circuits | C39: Moflic | D39: 2024 | E39: MSc/PhD thesis, Aalto University | F39: Thesis | G39: Other | H39: GS eq-check | I39: Maybe | J39: Compilation + equivalence checking (C6) | K39: aaltodoc.aalto.fi | L39: QEC-focused; compilation is secondary theme
A40: 39 | B40: Automated equivalence checking of concurrent quantum systems | C40: Ardeshir-Larijani, Gay, Nagarajan | D40: 2018 | E40: ACM Transactions on Computational Logic | F40: Journal | G40: ACM DL | H40: GS eq-check | I40: Yes | J40: Equivalence checking (C6), foundational | K40: dl.acm.org
A41: 40 | B41: Quantum circuit equivalence checking: A tractable bridge from unitary to hybrid circuits | C41: Ricciardi, Bardin, Chareton, Valiron | D41: 2025 | E41: arXiv | F41: Preprint | G41: arXiv | H41: GS eq-check | I41: Yes | J41: Equivalence checking (C6) | K41: arxiv.org
A42: 41 | B42: Efficient Transpilation of OpenQASM 3.0 Dynamic Circuits to CUDA-Q | C42: Kulkarni, Lee, Hutchings, Albahri et al. | D42: 2026 | E42: IEEE Conf. on Quantum Computing & Engineering (venue truncated) | F42: Conference | G42: IEEE Xplore | H42: GS eq-check | I42: Maybe | J42: Testing suite for transpiled circuits | K42: ieeexplore.ieee.org
A43: 42 | B43: Mutation-based test generation for quantum programs with multi-objective search | C43: Wang, Yu, Arcaini, Yue, Ali | D43: 2022 | E43: GECCO | F43: Conference | G43: ACM DL | H43: GS mutation | I43: Yes | J43: Mutation-based test generation (search-based) | K43: dl.acm.org
A44: 43 | B44: Testing and debugging quantum programs: The road to 2030 | C44: Ramalho, de Souza et al. | D44: 2025 | E44: ACM Transactions on Software Engineering and Methodology | F44: Journal | G44: ACM DL | H44: GS mutation | I44: Yes | J44: Testing/debugging roadmap (survey) | K44: dl.acm.org
A45: 44 | B45: QuanForge: A Mutation Testing Framework for Quantum Neural Networks | C45: Shao, Xia, Zhao | D45: 2026 | E45: Proceedings of the ACM on Software Engineering | F45: Conference | G45: ACM DL | H45: GS mutation | I45: Maybe | J45: Mutation testing (QNN, not compiler) | K45: dl.acm.org
A46: 45 | B46: Assessing the effectiveness of input and output coverage criteria for testing quantum programs | C46: Ali, Arcaini, Wang, Yue | D46: 2021 | E46: ICST | F46: Conference | G46: IEEE Xplore | H46: GS mutation | I46: Yes | J46: Coverage-criteria testing technique | K46: ieeexplore.ieee.org
A47: 46 | B47: Quantum software testing: State of the art | C47: Garcia de la Barrera, Garcia-Rodriguez de Guzman, Polo, Piattini | D47: 2023 | E47: Journal of Software: Evolution and Process | F47: Journal | G47: Wiley | H47: GS mutation | I47: Yes | J47: Survey (related SLR/mapping study) | K47: onlinelibrary.wiley.com | L47: Key related work for protocol novelty claim
A48: 47 | B48: A Comprehensive Analysis of Anomaly-Driven Fuzzing for Quantum Circuits | C48: Pudukotai Dinakarrao, Lalichetti | D48: 2026 | E48: Great Lakes Symposium on VLSI (GLSVLSI) | F48: Conference | G48: ACM DL | H48: GS fuzzing | I48: Yes | J48: Anomaly-driven fuzzing (C1) | K48: dl.acm.org
A49: 48 | B49: An automata-based framework for verification and bug hunting in quantum circuits | C49: Chen, Chung, Lengal, Lin et al. | D49: 2023 | E49: PLDI (PACMPL) | F49: Conference | G49: ACM DL | H49: GS fuzzing | I49: Yes | J49: Automata-based verification / bug hunting (C6/C7) | K49: dl.acm.org
A50: 49 | B50: QuanFuzz: Fuzz testing of quantum program | C50: Wang, Gao, Jiang, Lou, Gao, Zhang et al. | D50: 2018 | E50: arXiv | F50: Preprint | G50: arXiv | H50: GS fuzzing | I50: Yes | J50: Fuzzing (C1), early/foundational | K50: arxiv.org
A51: 50 | B51: A methodological analysis of empirical studies in quantum software testing | C51: Li, Shao, Zhao, Wang | D51: 2026 | E51: ACM Transactions on Software Engineering and Methodology | F51: Journal | G51: ACM DL | H51: GS regression | I51: Yes | J51: Methodological analysis (meta/survey) | K51: dl.acm.org
A52: 51 | B52: Metamorphic testing of oracle quantum programs | C52: Abreu, Fernandes, Llana | D52: 2022 | E52: Int'l Workshop on Quantum Software Engineering (ICSE Workshops) | F52: Workshop | G52: ACM DL | H52: GS metamorphic | I52: Yes | J52: Metamorphic testing, oracle-specific (C3) | K52: dl.acm.org
A53: 52 | B53: Asserting the correctness of shor implementations using metamorphic testing | C53: Costa, Fernandes, Abreu | D53: 2022 | E53: Int'l Workshop on Quantum Programming and Software Engineering | F53: Workshop | G53: ACM DL | H53: GS metamorphic | I53: Maybe | J53: Metamorphic testing, algorithm-specific (C3) | K53: dl.acm.org | L53: Tests an algorithm implementation, not the compiler
A54: 53 | B54: MetaMorphQ: Physics-Based Metamorphic Testing of Variational Quantum Circuits | C54: Nguyen, Le, Vu, Nguyen et al. | D54: 2026 | E54: arXiv | F54: Preprint | G54: arXiv | H54: GS metamorphic | I54: Maybe | J54: Metamorphic testing, physics-based (C3) | K54: arxiv.org | L54: VQC-focused, not compiler-specific
A55: 54 | B55: Quantum Testing and Validation | C55: Jayasena, Andrews, Mishra | D55: 2026 | E55: Design Automation for Quantum Computing (Springer book) | F55: Book chapter | G55: SpringerLink | H55: GS metamorphic | I55: Yes (secondary) | J55: Testing & validation overview (background) | K55: link.springer.com
A56: 55 | B56: Generating Metamorphic Test Cases using 2-qubit Quantum Gate Combinations | C56: Hyun, Kang | D56: 2026 | E56: Journal of The Korea Society of Computer and Information | F56: Journal | G56: Other | H56: GS metamorphic | I56: Maybe | J56: Metamorphic test generation, gate-level (C3) | K56: dbpia.co.kr
A57: 56 | B57: Enhancing Differential Testing Through Domain-Specific Equivalence Rules | C57: J Wang | D57: 2025 | E57: PhD thesis, Purdue University | F57: Thesis | G57: Other | H57: GS diff-test | I57: Yes | J57: Differential testing + equivalence rules (C2) | K57: search.proquest.com
A58: 57 | B58: Fuzzing-based differential testing for quantum simulators | C58: Blackwell, Petke, Cao, Bensoussan | D58: 2024 | E58: Springer conference (venue truncated in listing) | F58: Conference | G58: SpringerLink | H58: GS diff-test | I58: Yes (secondary) | J58: Fuzzing + differential testing | K58: link.springer.com | L58: Targets simulators via OpenQASM 3 IR
A59: 58 | B59: Delta debugging for property-based regression testing of quantum programs | C59: Pontolillo, Mousavi | D59: 2024 | E59: Int'l Workshop on Quantum Software Engineering (IWQS) | F59: Workshop | G59: ACM DL | H59: GS prop-test | I59: Yes | J59: Property-based + regression testing (C5/C8 intersection) | K59: dl.acm.org | L59: Directly relevant to RQ3/C8 lineage
A60: 59 | B60: A multi-lingual benchmark for property-based testing of quantum programs | C60: Pontolillo, Mousavi | D60: 2022 | E60: Int'l Workshop on Quantum Software Engineering (IWQS) | F60: Workshop | G60: ACM DL | H60: GS prop-test | I60: Yes | J60: Property-based testing benchmark (C5, RQ4) | K60: dl.acm.org
A61: 60 | B61: From ideal to noisy: Adapting property-based testing for real-world noisy quantum computers | C61: Pontolillo, Muqeet, Ali et al. | D61: 2025 | E61: IEEE Conf. on Quantum Computing & Engineering (QCE) | F61: Conference | G61: IEEE Xplore | H61: GS prop-test | I61: Yes | J61: Property-based testing, ML-guided (C5) | K61: ieeexplore.ieee.org
A62: 61 | B62: Generating Property-Based Tests for Quantum Algorithms | C62: Garcia de la Barrera, Serrano et al. | D62: 2024 | E62: Int'l Conf. on Service-Oriented Computing (ICSOC) | F62: Conference | G62: SpringerLink | H62: GS prop-test | I62: Yes | J62: Property-based test generation (C5) | K62: link.springer.com
A63: 62 | B63: Quantum testing in the wild: a case study with Qiskit algorithms | C63: Ramalho, da Silva et al. | D63: 2025 | E63: IEEE Software Testing conference (venue truncated in listing) | F63: Conference | G63: IEEE Xplore | H63: GS prop-test | I63: Yes | J63: Empirical case study (RQ1) | K63: ieeexplore.ieee.org
A64: 63 | B64: Benchmarking Quantum Software Testing with Scalable Quantum Programs | C64: Li, Shao, Li, Zhao, Cai | D64: 2026 | E64: arXiv | F64: Preprint | G64: arXiv | H64: GS prop-test | I64: Yes | J64: Benchmark (RQ4) | K64: arxiv.org
A65: 64 | B65: An open-source, industrial-strength optimizing compiler for quantum programs | C65: Smith, Peterson, Skilbeck et al. | D65: 2020 | E65: Quantum Science and Technology | F65: Journal | G65: Other | H65: GS emi | I65: Yes (secondary) | J65: Compiler equivalence testing (Quilc) | K65: iopscience.iop.org | L65: IOP journal; tests Quilc via equivalence holistically
A66: 65 | B66: Catching Transpilation Drift with a CI/CD Workflow in Quantum Software Development | C66: Peltonen, Kinanen, Stirbu | D66: 2026 | E66: arXiv | F66: Preprint | G66: arXiv | H66: GS qiskit-bug | I66: Yes | J66: Regression / drift detection, CI-CD (C8, RQ3) | K66: arxiv.org | L66: Directly targets transpilation regression in CI/CD
A67: 66 | B67: Regression testing of an evolving quantum platform | C67: Kitt | D67: 2024 | E67: MSc thesis, Iowa State University | F67: Thesis | G67: Other | H67: GS qiskit-bug | I67: Yes | J67: Regression testing of quantum compiler (RQ3/C8) | K67: search.proquest.com | L67: Same author as MorphQ++; broader regression-testing methodology
A68: 67 | B68: Backend-Aware Graph Learning for Denoising Outcome Distributions in Quantum Program Testing | C68: Ma, Dai, Li | D68: 2026 | E68: arXiv | F68: Preprint | G68: arXiv | H68: GS qiskit-bug | I68: Maybe | J68: ML-based testing / denoising (secondary) | K68: arxiv.org
A69: 68 | B69: QBugLM: An Agentic Benchmarking Framework for LLM-based Quantum Software Debugging | C69: Pham, Nguyen, Usman | D69: 2026 | E69: arXiv | F69: Preprint | G69: arXiv | H69: GS qiskit-bug | I69: Yes (secondary) | J69: LLM-based debugging benchmark (RQ4) | K69: arxiv.org
A70: 69 | B70: Reproducible builds for quantum computing | C70: Veiga, Hanggi | D70: 2025 | E70: arXiv | F70: Preprint | G70: arXiv | H70: GS qiskit-bug | I70: Maybe | J70: Build reproducibility / supply-chain (secondary) | K70: arxiv.org
A71: 70 | B71: Characterizing Bugs and Quality Attributes in Quantum Software: A Large-Scale Empirical Study | C71: Yousuf, Sofi | D71: 2025 | E71: arXiv | F71: Preprint | G71: arXiv | H71: GS qiskit-bug | I71: Yes (secondary) | J71: Empirical bug study (RQ1) | K71: arxiv.org
A72: 71 | B72: AssertsQ: A Quantum Assertion Tool for Quantum Software Debugging | C72: Veganzones, Alamo, Cuzzocrea, Bringas | D72: 2025 | E72: IQSOFT | F72: Conference | G72: Other | H72: GS qbug p2 | I72: Yes | J72: Assertion-based debugging tool (RQ2) | K72: scitepress.org
A73: 72 | B73: Understanding Bugs in Quantum Simulators: An Empirical Study | C73: Upadhyay, Fakorede, Farooq | D73: 2026 | E73: arXiv | F73: Preprint | G73: arXiv | H73: GS qbug p2 | I73: Yes (secondary) | J73: Empirical bug study (simulators) | K73: arxiv.org
A74: 73 | B74: Inverse-transpilation: reverse-engineering quantum compiler optimization passes from circuit snapshots | C74: Kundu, Ghosh | D74: 2025 | E74: Great Lakes Symposium on VLSI (GLSVLSI) | F74: Conference | G74: ACM DL | H74: GS qbug p2 | I74: Maybe | J74: Reverse-engineering compiler passes (secondary) | K74: dl.acm.org
A75: 74 | B75: Probabilistic Condition, Decision and Path Coverage of Circuit-based Quantum Programs | C75: Fortunato, Campos, Abreu | D75: 2026 | E75: arXiv | F75: Preprint | G75: arXiv | H75: GS qbug p2 | I75: Yes | J75: Structural coverage criteria (testing technique) | K75: arxiv.org | L75: Cites regression testing / test prioritisation as related uses
A76: 75 | B76: Transpiling OpenQASM 3.0 programs to CUDA-Q kernels | C76: Arulandu | D76: 2024 | E76: Technical report | F76: Preprint | G76: Other | H76: GS qbug p2 | I76: Maybe | J76: Transpiler bug-finding narrative (secondary) | K76: arulandu.com
A77: 76 | B77: Towards Quantum Program Bug Datasets and Benchmarking | C77: Li, Yu, Fan, Wang, Zhai, Zhang et al. | D77: 2026 | E77: ACM proceedings (venue truncated in listing) | F77: Conference | G77: ACM DL | H77: GS qbug p2 | I77: Yes | J77: Bug dataset / benchmark, QBench (RQ4) | K77: dl.acm.org
A78: 77 | B78: Bug Classification in quantum software: a rule-based framework and its evaluation | C78: Yousuf, Sofi | D78: 2026 | E78: Automated Software Engineering | F78: Journal | G78: SpringerLink | H78: GS qbug p2 | I78: Yes | J78: Bug taxonomy, rule-based (RQ1/RQ4) | K78: link.springer.com | L78: Same author pair as the Characterizing Bugs empirical study already in this corpus
A79: 78 | B79: QUTest: A Native Testing Framework for Quantum Programs | C79: Campos | D79: 2026 | E79: arXiv | F79: Preprint | G79: arXiv | H79: GS qbug p3 | I79: Yes | J79: Native testing framework for QPs (RQ1) | K79: arxiv.org | L79: Mentions a QAOA migration regression
A80: 79 | B80: Isolating Recurring Execution-Dependent Abnormal Patterns on NISQ Quantum Devices | C80: Qi, Li, Islam, Zhang, He, Wang | D80: 2026 | E80: arXiv | F80: Preprint | G80: arXiv | H80: GS qbug p3 | I80: Maybe | J80: Execution-pattern testing on NISQ devices (secondary) | K80: arxiv.org
A81: 80 | B81: KQFuzz: Knowledge-Guided Fuzzing for Quantum Libraries via Large Language Models | C81: Xia, Zhang, Ying, Zhu, Wang, Luo et al. | D81: 2026 | E81: arXiv | F81: Preprint | G81: arXiv | H81: GS llm-test | I81: Yes | J81: LLM-guided fuzzing (C1 variant) | K81: arxiv.org
A82: 81 | B82: Large Language Models for Quantum Software Engineering: Opportunities and Challenges in Modeling, Generation, Testing, and Repair | C82: Ye, Hu, Zhang, Xia, Guo, Wu et al. | D82: 2026 | E82: ACM Transactions on Software Engineering and Methodology | F82: Journal | G82: ACM DL | H82: GS llm-test | I82: Yes | J82: Survey - LLMs for testing / repair | K82: dl.acm.org
A83: 82 | B83: Fuzz4all: Universal fuzzing with large language models | C83: Xia, Paltenghi, Le Tian, Pradel et al. | D83: 2024 | E83: ICSE | F83: Conference | G83: IEEE Xplore | H83: GS llm-test | I83: Yes | J83: Universal LLM-guided fuzzing incl. quantum (C1) | K83: dl.acm.org | L83: 525 citations; reports low validity rate fuzzing quantum code
A84: 83 | B84: Generative AI for quantum circuits and quantum code: A technical review and taxonomy | C84: Merilehto | D84: 2026 | E84: arXiv | F84: Preprint | G84: arXiv | H84: GS llm-test | I84: Maybe | J84: Survey / taxonomy (background) | K84: arxiv.org
A85: 84 | B85: Quanbench: Benchmarking quantum code generation with large language models | C85: Guo, Wang, Zhao | D85: 2025 | E85: ASE | F85: Conference | G85: IEEE Xplore | H85: GS llm-test | I85: Maybe | J85: Code-gen benchmark with compile-success metric (secondary) | K85: ieeexplore.ieee.org
A86: 85 | B86: Testing and debugging quantum circuits | C86: Metwalli, Van Meter | D86: 2024 | E86: IEEE Transactions on Quantum Engineering | F86: Journal | G86: IEEE Xplore | H86: GS qbug p4 | I86: Yes | J86: Testing/debugging framework, transpiler debugger (RQ1/RQ2) | K86: ieeexplore.ieee.org
A87: 86 | B87: Intent-Level Quantum Programming with Assertion-Guided Execution and Inspectable Intermediate Representation | C87: Vora, Thudumu, Carlson, Kamdar et al. | D87: 2026 | E87: arXiv | F87: Preprint | G87: arXiv | H87: GS qbug p4 | I87: Yes (secondary) | J87: Assertion-guided execution + regression testing (secondary) | K87: arxiv.org
A88: 87 | B88: Beyond Rules: LLM-Powered Linting for Quantum Programs | C88: Cassieri, Scanniello, Shin, Pastore et al. | D88: 2026 | E88: arXiv | F88: Preprint | G88: arXiv | H88: GS qbug p4 | I88: Yes (secondary) | J88: LLM-based static analysis / linting (secondary) | K88: arxiv.org
A89: 88 | B89: A Survey of Functional Testing and Validation of Quantum Circuits | C89: Andrews, Jayasena, Mishra | D89: 2026 | E89: IEEE Design & Test | F89: Journal | G89: IEEE Xplore | H89: GS qbug p4 | I89: Yes | J89: Survey - functional testing and validation | K89: ieeexplore.ieee.org | L89: Companion survey to this team's Design Automation for Quantum Computing book chapter already in corpus
A90: 89 | B90: A Validated Measurement Protocol for Comparable, Cost-Aware Software Testing Evaluation: A Reproducible Benchmark and Oracle Sampling-Budget Guarantee | C90: Gupta, Rana | D90: 2026 | E90: Research Square preprint | F90: Preprint | G90: Other | H90: GS qbug p4 | I90: Yes | J90: Cost-aware testing evaluation protocol, uses Bugs4Q (RQ3/RQ4) | K90: researchsquare.com
A91: 90 | B91: Verification Paradigms for Quantum Computing | C91: Choudhury, Bhave, Basu | D91: 2026 | E91: Design Automation for Quantum Computing (Springer book) | F91: Book chapter | G91: SpringerLink | H91: GS qbug p5 | I91: Yes | J91: Verification paradigms overview incl. regression-testing framework (background) | K91: link.springer.com | L91: Same author team as Concolic testing for quantum compilers and QuaSi already in corpus
A92: 91 | B92: Automatic repair of quantum programs via unitary operation | C92: Li, Pei, Huang, Yin, Cai | D92: 2024 | E92: ACM Transactions on Software Engineering and Methodology | F92: Journal | G92: ACM DL | H92: GS qbug p5 | I92: Yes | J92: Automated program repair, bug-pattern taxonomy (RQ1/RQ4) | K92: dl.acm.org
A93: 92 | B93: QUAMET: Structural and Semantic Metric Analysis for Quantum Code Smell Detection | C93: Malhotra, Jain, Kessentini | D93: 2026 | E93: Research Square preprint | F93: Preprint | G93: Other | H93: GS qbug p5 | I93: Yes (secondary) | J93: Code smell / static analysis detection (secondary) | K93: researchsquare.com
A94: 93 | B94: Qchecker: Detecting bugs in quantum programs via static analysis | C94: Zhao, Wu, Li, Zhao | D94: 2023 | E94: IEEE/ACM Int'l Workshop on Quantum Software Engineering (Q-SE) | F94: Workshop | G94: IEEE Xplore | H94: GS static-analysis | I94: Yes | J94: Static analysis bug detection (RQ1) | K94: ieeexplore.ieee.org
A95: 94 | B95: Analyzing quantum programs with LintQ: A static analysis framework for Qiskit | C95: Paltenghi, Pradel | D95: 2024 | E95: FSE (Proceedings of the ACM on Software Engineering) | F95: Conference | G95: ACM DL | H95: GS static-analysis | I95: Yes | J95: Static analysis framework (RQ1) | K95: dl.acm.org
A96: 95 | B96: Supporting static program analysis and transformation of quantum-based languages | C96: Behler, Al-Ramadan, Baheri et al. | D96: 2024 | E96: IEEE Int'l Workshop on Quantum Software Engineering | F96: Workshop | G96: IEEE Xplore | H96: GS static-analysis | I96: Yes (secondary) | J96: Static analysis framework (RQ1) | K96: ieeexplore.ieee.org
A97: 96 | B97: Identifying bug patterns in quantum programs | C97: Zhao, Zhao, Ma | D97: 2021 | E97: IEEE/ACM Int'l Workshop on Quantum Software Engineering (Q-SE) | F97: Workshop | G97: IEEE Xplore | H97: GS static-analysis | I97: Yes | J97: Bug-pattern taxonomy, foundational (RQ1) | K97: ieeexplore.ieee.org | L97: 91 citations; precedes QChecker
A98: 97 | B98: Towards defect prediction for quantum software | C98: Mao, Huang, Ge, Wang et al. | D98: 2025 | E98: IEEE Int'l Workshop on Quantum Software Engineering | F98: Workshop | G98: IEEE Xplore | H98: GS static-analysis | I98: Yes (secondary) | J98: Defect prediction (RQ1) | K98: ieeexplore.ieee.org
A99: 98 | B99: Quantum Software Engineering: Developing Algorithms for IBM Quantum Systems | C99: Khan | D99: 2025 | E99: SSRN working paper | F99: Preprint | G99: SSRN | H99: GS ci-regression | I99: Maybe | J99: Background / overview (secondary) | K99: papers.ssrn.com
A100: 99 | B100: QC-MM: A Metadata and Schema Model for Traceable Quantum-Circuit Experiments | C100: Huenchuleo, Sepulveda, Fernandez | D100: 2026 | E100: Applied Sciences (MDPI) | F100: Journal | G100: Other | H100: GS ci-regression | I100: Maybe | J100: Metadata / traceability infrastructure (secondary) | K100: mdpi.com
...

Sheet Summary
A1: Scoping corpus — where the papers are published
A2: Counts computed live from the Corpus tab (COUNTIF). Edit Corpus and re-open to refresh.
A4: Publisher / Index | B4: Papers | D4: Type | E4: Papers | G4: Relevance | H4: Papers
A5: IEEE Xplore | B5: =COUNTIF(Corpus!$G$2:$G$301,A5) -> 78 | D5: Journal | E5: =COUNTIF(Corpus!$F$2:$F$301,D5) -> 65 | G5: Yes | H5: =COUNTIF(Corpus!$I$2:$I$301,G5) -> 237
A6: ACM DL | B6: =COUNTIF(Corpus!$G$2:$G$301,A6) -> 72 | D6: Conference | E6: =COUNTIF(Corpus!$F$2:$F$301,D6) -> 112 | G6: Yes (secondary) | H6: =COUNTIF(Corpus!$I$2:$I$301,G6) -> 16
A7: SpringerLink | B7: =COUNTIF(Corpus!$G$2:$G$301,A7) -> 35 | D7: Workshop | E7: =COUNTIF(Corpus!$F$2:$F$301,D7) -> 28 | G7: Maybe | H7: =COUNTIF(Corpus!$I$2:$I$301,G7) -> 47
A8: Springer Nature (Nature) | B8: =COUNTIF(Corpus!$G$2:$G$301,A8) -> 1 | D8: Preprint | E8: =COUNTIF(Corpus!$F$2:$F$301,D8) -> 75 | G8: Total | H8: =SUM(H5:H7) -> 300
A9: ScienceDirect (Elsevier) | B9: =COUNTIF(Corpus!$G$2:$G$301,A9) -> 1 | D9: Preprint (survey) | E9: =COUNTIF(Corpus!$F$2:$F$301,D9) -> 2
A10: arXiv | B10: =COUNTIF(Corpus!$G$2:$G$301,A10) -> 68 | D10: Thesis | E10: =COUNTIF(Corpus!$F$2:$F$301,D10) -> 12
A11: SSRN | B11: =COUNTIF(Corpus!$G$2:$G$301,A11) -> 2 | D11: Book chapter | E11: =COUNTIF(Corpus!$F$2:$F$301,D11) -> 6
A12: Wiley | B12: =COUNTIF(Corpus!$G$2:$G$301,A12) -> 1 | D12: Total | E12: =SUM(E5:E11) -> 300
A13: Other | B13: =COUNTIF(Corpus!$G$2:$G$301,A13) -> 42
A14: Total | B14: =SUM(B5:B13) -> 300
A17: By year
A18: Year | B18: Papers
A19: 2015 | B19: =COUNTIF(Corpus!$D$2:$D$301,A19) -> 0
A20: 2016 | B20: =COUNTIF(Corpus!$D$2:$D$301,A20) -> 0
A21: 2017 | B21: =COUNTIF(Corpus!$D$2:$D$301,A21) -> 0
A22: 2018 | B22: =COUNTIF(Corpus!$D$2:$D$301,A22) -> 3
A23: 2019 | B23: =COUNTIF(Corpus!$D$2:$D$301,A23) -> 8
A24: 2020 | B24: =COUNTIF(Corpus!$D$2:$D$301,A24) -> 10
A25: 2021 | B25: =COUNTIF(Corpus!$D$2:$D$301,A25) -> 20
A26: 2022 | B26: =COUNTIF(Corpus!$D$2:$D$301,A26) -> 26
A27: 2023 | B27: =COUNTIF(Corpus!$D$2:$D$301,A27) -> 30
A28: 2024 | B28: =COUNTIF(Corpus!$D$2:$D$301,A28) -> 52
A29: 2025 | B29: =COUNTIF(Corpus!$D$2:$D$301,A29) -> 70
A30: 2026 | B30: =COUNTIF(Corpus!$D$2:$D$301,A30) -> 81
A31: Total | B31: =SUM(B19:B30) -> 300
A32: Screened but excluded (off-topic / not related to SLR)
A33: Round | B33: Excluded (irrelevant) | D33: Notes
A34: 1-6 | B34: (not logged) | D34: Exclusions were not separately logged during rounds 1-6 — only included/screened-in papers were recorded at the time. Running total starts from Round 7.
A35: 7 | B35: 8 | D35: Off-topic/too-broad hits from the 5 new queries this round: 4 quantum-SE/QC surveys too broad to be testing-specific (Gill et al. taxonomy, Salam & Ilyas MLR, Dwivedi et al. lifecycle survey, Mandal et al. SE review), 1 tangential ML-platform paper (QuantuMoonLight), 1 non-research editorial (Eldh), 1 hardware performance-benchmark paper (Lubinski et al.), 1 compiler-architecture paper without a testing focus (Scheller et al.). Duplicates of papers already in the corpus are not counted here (tracked separately as screening dedupe, not exclusion).
A36: 8 | B36: 14 | D36: Off-topic hits from the 5 new round-8 queries: 6 QML-training/hardware-physics papers with no software-testing focus (Dalyac et al., Khanal, Ayral et al., QuantumNAT, RobustState, RoQNN), 2 symbolic-execution/formalism papers too theoretical or too broad to be testing-specific (Ying 2025 symbolic specification, Miszczak symbolic programming), 1 broad quantum-systems review (Yin et al.), 2 broad/low-tier framework overview articles (Rusum & Anasuri, Nalwade & Upoma), and 3 classical (non-quantum) compiler-fuzzing papers returned by the PennyLane/Braket query (Cummins et al., Ye et al., Palka et al.) that are out of scope by design. Duplicates of papers already in the corpus are not counted here.
A37: 9 | B37: 5 | D37: Off-topic hits from the 5 new round-9 queries: 1 tangential LLM circuit-generation paper (Macarone-Palmieri & Franco, not a testing study), 1 design-patterns case study with no testing focus (Fernandez-Osuna et al.), 1 quantum-annealing-for-classical-test-suite-optimization paper excluded per the protocol's Table 6 confound rule (Trovato et al. — quantum optimisation applied to classical testing, not testing of quantum software), 1 broad open-source-ecosystem landscape paper (Fingerhuth et al., testing is a minor aspect among many), and 1 broad PhD dissertation on heterogeneous-computing testing/debugging that overlaps material already captured via its constituent QDiff and equivalence-rules papers already in the corpus (Wang J. dissertation). Duplicates of papers already in the corpus (including same-author thesis/technical-report/artifact companions) are not counted here.
A38: 10 | B38: 49 | D38: Round 10 ran 10 queries (two batches of 5) targeting: metamorphic relations for Shor/Grover, VQE/QAOA testing/validation, test-case prioritisation/selection, error-mitigation (ZNE) testing, runtime verification, test-oracle generation, search-based/genetic test generation, unit-testing frameworks, CI adoption empirical studies, and design-by-contract. Two query angles turned out to probe adjacent-but-out-of-scope literatures almost entirely: (a) VQE/QAOA 'testing/validation' and error-mitigation (ZNE) 'testing' mostly return physics/algorithm-performance benchmarking papers, not software-testing-of-compilers papers (13 excluded across these two queries); (b) test-case prioritisation/selection returns almost exclusively the quantum-annealing-for-classical-test-suite-optimization confound already flagged by the protocol's Table 6 exclusion rule, plus two classical quantum-behaved-PSO papers that are not quantum computing at all (9 excluded). Also excluded: 3 post-quantum-cryptography hits misidentified by keyword overlap ('quantum' meaning quantum-resistant classical crypto, not quantum computing: Pugh et al., Abela et al., Sun et al.), 1 false-positive keyword match unrelated to quantum computing (Platzer — 'Quantum' is a variable name in a cyber-physical-systems example), several QNN/architecture-search papers using genetic algorithms for circuit optimisation rather than testing, 8 classical (non-quantum) CI-adoption empirical studies returned by the CI query, and a handful of broad roadmap/ecosystem/toolchain/pattern-catalog papers with no testing focus. Duplicates of papers already in the corpus (including same-author thesis/preprint/poster companions) are not counted here.
A39: 11 | B39: 16 | D39: Off-topic hits from the 5 new round-11 queries: 1 pure-theory ZX-calculus completeness proof with no testing/verification-tool angle (Wang 2022), 5 classical (non-quantum-specific) LLM-code-generation/testing surveys and tools returned by the Copilot query (Fan et al., Wang et al., Agarwal et al., Menet et al., Mathews), and 10 quantum-compiler qubit-allocation/mapping algorithm-design papers returned by the qubit-placement query that address compiler heuristics and their empirical performance rather than a testing methodology (Murali et al., LeCompte et al., Chipmunq, QuantEM, 2qan, Siraichi et al., Zhu et al. survey, Wille et al., FQAS, Promponas et al.) — this negative finding narrows the qubit-mapping literature to a compiler-design topic distinct from our testing/verification scope. The GitHub-issue/transpiler-bug empirical-mining query returned zero new papers, all 10 hits already captured in the corpus from earlier rounds — a useful signal that this vein is now saturated. Duplicates of papers already in the corpus (including same-author thesis/book-chapter companions) are not counted here.
A40: 12 | B40: 12 | D40: Round 12 was a short targeted round (3 queries) run to close the gap to the user's requested 200-row target: Clifford/stabilizer circuit verification, compiler rewrite-rule correctness (peephole optimization), and a second page of the round-9 circuit-synthesis query. Excluded: 6 physics/complexity-theory papers using 'verification'/'testing' in the quantum-information-theory sense (property testing of Clifford-ness, QMA complexity, fault-tolerance benchmarking) rather than the software-testing sense (Xiao et al., Brown et al., Yan, Sun et al., Arunachalam et al., Kuehnke et al.), 1 classical (non-quantum) SSA-compiler peephole-rewriting paper that mentions quantum computing only as one example domain in passing (Bhat et al.), and 4 circuit-synthesis papers whose 'testing'/'accuracy' language refers to ML-model evaluation or general design-space exploration rather than software testing (da Cruz thesis, Weiden et al., Hwang, Islam et al.), plus one 2006 citation-only stub predating the SLR's 2015 search-window floor (Hayes & Markov). Duplicates of papers already in the corpus are not counted here.
A41: 13 | B41: 10 | D41: Round 13 (5 queries: fault injection, test-suite reduction, cross-version regression, SDK fuzzing, QEC decoder testing) confirmed two veins are now saturated with zero new papers (cross-version Qiskit-regression-testing, general fuzzing) — all hits were duplicates already in the corpus. Excluded: 1 security/adversarial fault-injection-attack paper (not a testing methodology study; Etim & Szefer), 1 physics/QEC-code-design paper (Ginsberg & Patel), 2 more instances of the quantum-annealing/QAOA-for-classical-test-suite-minimization confound (Sharma et al., Hussein et al.), 2 pre-2015 quantum-inspired-GA test-suite papers (also confound; Zhang et al. 2011, Kumari et al. 2012), and 4 hardware/physics QEC-decoder papers using 'testing' in the physics-experiment sense rather than software-testing sense (the Google below-threshold QEC paper, Bausch et al., Ryan-Anderson et al., Cruz et al.). Duplicates already in the corpus are not counted here.
A42: 14 | B42: 29 | D42: Round 14 (5 queries: QKD/quantum-cryptography testing, mock/test-double backends, comparative tool-evaluation surveys, pytket/tket-specific, TDD-practices) surfaced two important scope boundaries. First, quantum key distribution and quantum networking are a different subfield (quantum communication/cryptography hardware) from quantum-computing compiler/transpiler testing and returned zero relevant hits — all 10 QKD-query results excluded, including one post-quantum-cryptography false-positive (Bhargavan et al., 'quantum' meaning quantum-resistant classical crypto) and quantum-internet infrastructure (Dahlberg & Wehner, excluded from the backend-mocking query). Second, the test-driven-development-practices query returned almost entirely classical (non-quantum) TDD empirical literature, including several false-positive matches where 'quantum' appeared only as an ordinary English phrase ('quantum of work') rather than referring to quantum computing (Bhadauria, Ahmed et al.) — all 10 hits excluded. Also excluded: 1 hardware/EDA circuit-design paper using Qiskit as an implementation platform rather than studying testing itself (Misra et al.), 3 simulator/HPC-infrastructure papers with no testing-methodology focus (Shehata et al., Guerreschi et al., Kumaresan et al.), 2 broad metrics/confound-survey papers (Soubra et al., Zhang et al. systematic analysis), and 2 compilation-performance/language-design papers with no testing focus (Moore et al., Guppy). Duplicates already in the corpus are not counted here.
A43: 15 | B43: 11 | D43: Round 15 (5 queries: model-based testing/FSM, type systems for no-cloning correctness, quantum Hoare/separation logic, white-box structural coverage, Q#-specific bug studies) opened a substantial new formal-verification vein: quantum Hoare logic and separation logic (7 papers, including two highly-cited foundational works, Liu et al. 2019 CAV and Unruh 2019 POPL) and a type-systems/no-cloning-correctness cluster (6 papers). Excluded: 7 classical (non-quantum) finite-state-machine/model-based-testing papers returned by the MBT query, most with no quantum content at all or only a passing unrelated mention (Turker et al., Giorgio, Huang & Peleska, Sabbaghi & Keyvanpour, Onofrei et al., Salem), 1 pre-2015 foundational thesis (Valiron 2008) and 1 pre-2015 foundational Hoare-logic paper (Ying 2012, Floyd-Hoare logic — 301 citations but outside the SLR's 2015 search-window floor), 1 too-broad general-overview book chapter (Ding & Chong), and 1 saturated-area PhD thesis judged redundant with primary papers already well-represented (El Aoun). Duplicates already in the corpus (including a same-author arXiv companion of an included thesis) are not counted here.
A44: 16 | B44: 9 | D44: Round 16 (2 queries: weakest-precondition calculus, bisimulation/process-calculus verification) extended the Hoare-logic vein with a refinement-calculus/weakest-precondition cluster (6 papers). The bisimulation query showed that quantum process-calculus/bisimulation work is predominantly a cryptographic-protocol-verification subfield (bit commitment, LOQC, security proofs) distinct from compiler/software-testing, and skews heavily pre-2015 (foundational theory from 2006-2012) — 8 of 10 hits excluded on those two grounds (Tedeschi, Puthoor, Davidson, Kubota et al., Feng et al. 2011/2012, Vitale, Lalire), plus 1 pre-2015 foundational weakest-precondition paper (D'hondt & Panangaden 2006). Duplicates already in the corpus are not counted here.
A45: 17 | B45: 2 | D45: Round 17 (1 query: second page of the Hoare/separation-logic search) closed out the formal-verification growth push. Excluded: 1 pre-2015 foundational Hoare-logic preprint (Ying 2009, precursor to the already-excluded 2012 journal version) and 1 classical C-program verification tool that only borrows a quantum-adjacent proof technique rather than verifying quantum programs itself (QCP). Duplicates already in the corpus are not counted here. Corpus reached the user's requested 240-row target at 245 rows.
A46: 18 | B46: 23 | D46: Round 18 (5 queries: circuit cutting/knitting, OpenQASM parser correctness, RL test generation, technical-debt/maintainability empirical, resource-estimation correctness) found that circuit-cutting (7 excluded) and RL-for-quantum-programs (6 excluded) and lattice-surgery resource-estimation (6 excluded) are each predominantly compiler-optimization/technique subfields rather than testing-methodology subfields — most hits describe or evaluate a new optimization/synthesis/estimation technique's own performance rather than contributing a testing method (DistributedEstimator, Liu et al., Cantori et al., Ren et al., Cutqc, Shehzad et al., Qrcc for circuit-cutting; McKiernan et al., Patel et al. CRLQAS, Pozzi et al., Kuo et al., Niu et al., Moro et al. for RL; Chong et al. roadmap, Meuli et al. [explicitly not about correctness], two LeBlond et al. lattice-surgery papers, Baldwin et al. quantum-volume hardware benchmark, Robertson et al. for resource estimation). Also excluded: 1 architecture-decision paper (Aktar et al.) and 3 classical (non-quantum) technical-debt papers (Vala et al., Bogner et al., Edbert et al.). Duplicates already in the corpus are not counted here.
A47: 19 | B47: 15 | D47: Round 19 (4 queries: quantum-state-tomography test oracles, universal-gate-set decomposition correctness, developer survey/interviews, cloud CI/DevOps for quantum) found that quantum state tomography is predominantly a complexity-theory/physics topic (property testing, sample complexity) rather than software testing — 6 of 9 hits excluded on that basis (Caro et al., Di Matteo thesis, Biamonte & Perkowski [pre-2015], Aaronson, Paler et al. [pre-2015], Rodrigues thesis), yielding zero new papers from that query. Also excluded: 1 redundant PhD-thesis compilation of already-included work by the same author (Shi 2020, overlaps CertiQ/Giallar already in the corpus), 1 unvetted single-author SSRN preprint of unclear rigor (PRIMITIVA-Q), 2 compiler-technique papers with no testing focus (Optimized compilation, Davis et al. heuristics), and from the cloud/DevOps query: 3 infrastructure/MLOps-platform papers with no testing-methodology content (Impedovo et al., Stirbu et al. Qubernetes), 1 quantum-resistant-security DevOps paper (Akbar et al. QSecOps — post-quantum security, not quantum-computing testing), and 1 low-credibility venue mismatch with only a passing quantum mention (Brijesh, Journal of Daoist Studies). Duplicates already in the corpus are not counted here.
A48: 20-21 | B48: 22 | D48: Rounds 20-21 (5 short queries closing the gap to the user's 270-row target: transpilation idempotence/stability, flaky-test root-cause taxonomy, D-Wave annealer embedding/compiler, SMT-solver-based test generation, no-cloning page 2, mutation-operator deep dive) confirmed flaky-test taxonomy and D-Wave-annealer-compilation are both fully saturated or out-of-scope: the flaky-test query returned only 1 new paper (a survey) with the rest duplicates, and the D-Wave query returned zero new papers — all 10 hits were classical-annealing compiler/hardware papers with no testing-methodology content (Baioletti & Santini, Pakin 2019, Hatzky, Yarkoni et al., Hassan et al., Jhaveri, Pakin & Reinhardt). The transpilation-idempotence query was similarly unproductive (9 excluded, mostly unrelated papers where 'transpile'/'regression' appeared incidentally in a physics/ML context, plus 1 redundant PhD-thesis compilation of already-included work, Metwalli 2024). The no-cloning page-2 and SMT-solver queries were more productive: SMT solvers for quantum-program verification/test-generation added 3 new papers, while the no-cloning follow-up drifted into quantum-information-theory/cryptography (7 excluded: Chatterjee et al., Lord, Morimae, Nehoran & Zhandry, Hettel, Garcia, Zhu & Wang) but still yielded 2 borderline additions. Duplicates already in the corpus (including a redundant PhD thesis by an author whose papers on SMT-based verification are already included, Lewis 2024) are not counted here.
A49: 22 | B49: 31 | C49: Round 22 (bug-prediction/defect, API-misuse/compatibility, hardware-specific superconducting/trapped-ion, PennyLane automatic-differentiation, and Grover-oracle test-generation queries) was the lowest-yield round to date: 2 new rows added against 31 exclusions (~6% hit rate, down from >50% in early rounds), signalling the corpus is approaching saturation for this search strategy. Confirmed two new confound-direction patterns mirroring the quantum-annealing-for-classical-test-case-prioritisation exclusion: (a) quantum/QML techniques applied to predict or classify defects in CLASSICAL software (Chaudhary et al.'s quantum-Hamiltonian-GAN defect predictor; Nadim's thesis and follow-up comparative QSVM study; El Ayachi & El Baz's entanglement-enhanced QSVM bug predictor) - these study quantum computing as a tool for classical SE, not testing of quantum software; (b) Grover's algorithm applied to CLASSICAL testing/EDA tasks (Miranskyy's Grover-accelerated dynamic testing of classical software; Manjunath & Bhowmik's Grover-based Automatic Test Pattern Generation for classical VLSI circuits). Also excluded: post-quantum-cryptography false positives (Toruan et al.'s PQC API usability study; de Bonrostro & González-Tablas' LLM-based PQC code migration); quantum-networking/control-plane infrastructure papers (Malarchick's control-plane-openness rubric; Ahmed et al.'s OSI redesign for quantum networks) rather than testing methodology; a classical AI-agent developer-challenges study (Asgari et al.) with no quantum computing content; a cluster of hardware-physics and gate-design papers returned by the superconducting/trapped-ion query (AbuGhanem's Mølmer-Sørensen gate paper, Mundada et al.'s error-suppression benchmarking) and several quantum-compiler-optimisation/hardware-mapping papers (Dalvi et al., Schmid et al., Xu et al.) that are compiler-design rather than testing contributions; and a cluster of PennyLane feature/tutorial/application papers returned by the automatic-differentiation query (the foundational PennyLane paper itself, plus differentiable-transforms, fidelity-susceptibility, anomaly-detection, and quantum-chemistry application papers, and a hybrid-ML tutorial guide) - automatic differentiation is a PennyLane feature, not a distinct testing-technique literature. New rows: a comprehensive empirical study of bug fixes in quantum programs (Luo et al., ICSME 2022, distinct from the bug-taxonomy/bug-report studies already in the corpus) and a thesis-level fine-grained analysis of bugs in open-source quantum projects covering API-misuse and design-pattern bugs (Camara, 2022, tagged Maybe given its thesis-compilation status).
A50: 23-24 | B50: 17 | C50: Rounds 23-24 (QML-adversarial-robustness, quantum-software-anti-patterns, simulator-numerical-precision, reproducibility/replication, quantum-cloud-API-testing, compiler-crash-bugs, OpenQASM/QIR-fuzzing, statistical-test-oracle/shots, QEC-verification/stabilizer, and Qiskit-issue-tracker/bug-triage queries) recovered a much better yield than round 22: 6 new rows against 17 exclusions (~26% hit rate), showing the corpus was not yet fully saturated on QEC-specific formal verification and statistical-test-oracle refinement sub-veins. Most hits in the crash-bugs, OpenQASM/QIR, and issue-tracker queries were confirmed duplicates of papers already in the corpus (MorphQ/MorphQ++, QEMI, the Paltenghi & Pradel bug-empirical/survey/IterTestQ cluster, the road-to-2030 roadmap, coverage-criteria and Quito papers, CUDA-Q statistical assertions, and the existing QEC symbolic-execution/formal-verification cluster), which is itself a useful saturation signal for those sub-veins. New rows: two simulator/numerical-correctness contributions (Klamroth & Beckert's rounding-error bounds for circuit simulation; a Bugs4Q dataset-reproducibility case study by Ohto et al.); two statistical-test-oracle extensions by the same author cluster as row 161 (Li, Cai & Yin's mixed-state test-preparation paper) and a unit-testing feasibility study (Miranskyy et al.); one QEC-specific verification contribution (Chancellor et al.'s ZX-calculus-based QEC design/verification paper, extending the equivalence-checking vein into error correction; a second candidate, Wu et al.'s Qecv framework, was caught during post-append verification as a row already present in the corpus at row 209 from an earlier round and was removed as a duplicate rather than double-counted); and a well-cited (66 citations) developer-challenges study mining Stack Exchange and GitHub issues (Li, Khomh & Openja, 2021), a data source distinct from the survey/interview studies already in the developer-experience cluster. Exclusions confirmed two new confound categories: adversarial-robustness/security evaluation of quantum machine learning models (a distinct ML-security subfield, not software-testing methodology - West et al., Nowmi et al., Weber et al., Lu/Duan/Deng, Marchiori & Conti, Dowling et al., Catak et al., and Guan/Fang/Ying's robustness-verification paper); and community/social smells in quantum open-source projects (Lambiase et al.) as distinct from code-level testing. Also excluded: design-pattern/architecture-analysis papers (Ramalho et al., Bühler et al., de Dieu et al.) as distinct from testing; general reproducibility/experiment-reporting papers not specific to testing (Gierisch & Mauerer's Qef, Moguel et al.'s laboratory-package guidelines, Köster et al., Vrtiak et al.); quantum-cloud-service/provider-comparison and architecture papers (Moguel et al., Alvarado-Valiente et al., Ahmad et al. x2, Hassan & Giri, Shinde & Szefer, Peltonen et al., Puligundla, Nguyen et al.) as infrastructure rather than testing contributions; QIR/OpenQASM compiler-infrastructure papers (Nguyen & McCaskey, Stade et al., Murillo et al.'s SE roadmap, Ayaz's thesis); QEC synthesis/benchmark papers (Peham et al., StabilizerBench) as compiler-optimisation rather than testing contributions; a low-credibility informal QEC verification writeup (Feng); a broad QEC design-automation survey (Ghosh et al.) and general QEC tutorial (Roffe); redundant PhD-thesis compilations (Paltenghi's thesis, El Aoun's thesis) whose content is already covered by their constituent published papers; a physics-informed neuro-fuzzy error-attribution paper (Hassan & Kaabouch) as physics/ML diagnosis rather than testing methodology; and several hardware/numerical-arithmetic papers unrelated to software testing returned by the numerical-precision query.
A51: 25 | B51: 21 | C51: Round 25 (debugging-tool/developer-experience comparison, bug-fix-pattern taxonomy, quantum-language-parser/frontend correctness, variational-quantum-circuit test generation, and mutation-testing-effectiveness queries) added 5 rows against 21 exclusions (~19% hit rate). The debugging-tool-comparison, fix-pattern, and mutation-testing-effectiveness angles were heavily saturated: nearly every hit (An experience-based classification of quantum bugs, Q-pac, QuanForge, Analyzing the evolution and maintenance of quantum software repositories, Quantum software engineering issues and challenges by De Stefano et al., Bugs4Q, QMutPy/the Fortunato et al. Qiskit mutation-testing case study, Quantum circuit mutants, the coverage-criteria and methodological-analysis papers, and Qcrmut) turned out to already be in the corpus from earlier rounds. Two new confound-adjacent boundaries confirmed by exclusion: quantum-language-parser/frontend correctness (Q#, Silq, and related DSL papers returned by that query) is dominated by programming-language-design contributions, not testing methodology, and variational-quantum-circuit 'test generation' queries return almost exclusively ansatz-design and algorithm-performance papers (a VQE/QAOA-adjacent confound already documented) rather than software-testing techniques - both angles yielded zero new rows despite a full page of results each. Also excluded: two broad roadmap/survey papers (a quantum-software-lifecycle survey by Dwivedi et al.; an LLM-for-quantum-SE opportunities paper by Ye et al. covering modeling/generation/testing/repair too broadly to count as a testing contribution) and several low-credibility or off-focus language-design theses and preprints (QCLang, Silq2Qiskit, a quantum-state-simulator thesis, a quantum-compilation-process survey, a practical-quantum-programming thesis, a QuSecVerify cybersecurity-framing paper, and others). New rows: a debugging-specific survey (Schrödinger's bug, Rosa & Santiago); a fault taxonomy specific to hybrid quantum-classical software architectures (Bensoussan et al., TOSEM); and three mutation-testing extensions not yet in the corpus - noise-aware mutation analysis (Fortz et al.), mutation testing applied to quantum machine learning models (Andrews & Mishra), and mutation-based fault localization for quantum programs (Ishimoto et al.).
A52: 26 | B52: 9 | C52: Round 26 (transpiler-optimization-level regression, LLM-based automated program repair, general quantum-software-testing-empirical-2026, cross-platform differential testing, and equivalence-checking scalability queries) hit the highest duplicate rate of any round to date: of roughly 45 distinct hits across the five queries, all but 5 were already present in the corpus. Confirmed near-total saturation of the transpiler-drift/regression, LLM-repair, cross-platform differential-testing, and ZX-calculus/equivalence-checking veins - essentially every well-known tool or paper in these spaces (QDiff, QSPE, QuaSi, QEMI, QuteFuzz, EriQua, MorphQ/MorphQ++, IterTestQ, Hornbro, the ChatGPT-repair and unitary-operation-repair papers, Transpilation Drift, the Bugs4Q/QBench dataset papers, and the core ZX-calculus/Clifford/model-counting equivalence-checking cluster including ZXNet) was already captured in earlier rounds. New rows: an LLM-repair paper that adds mutation analysis to guide patch generation (Yoshida et al.); a scalable shallow-circuit equivalence-checking method and its companion tool paper Manjushri (Yu, Trinh, Sistla & Reps, two rows from the same research cluster); a matrix-product-operator-based equivalence-checking technique (Sander, Burgholzer & Wille); and a practitioner study on test-oracle/output-validation adequacy for differential testing (Ye, Wu, Xia & Zhang). Exclusions confirmed the already-documented quantum-optimization-for-classical-SE and post-quantum-cryptography confounds (Zhang et al.'s systematic analysis of quantum optimization for software engineering; Wahlang & Vidhani's PQC code migration), classical (non-quantum) automated-program-repair papers returned by the LLM-repair query (Xia et al., Li et al.'s GiantRepair), a technology-adoption/SEM study (Lambiase & De Lucia) and an analyzability-model validation study (Díaz-Muñoz et al.) as distinct from testing methodology, and a low-credibility scoping review (Ogbodo et al., unfamiliar venue).
A53: 27 | B53: 16 | C53: Round 27 (circuit-cutting/distributed-computing correctness, general testing-tool-empirical-comparison, noise-aware-testing/NISQ-hardware, dataset/benchmark, and LLM-generated-quantum-code-correctness-evaluation queries) was the best-yield round since round 11, adding 9 rows against 16 exclusions (~36% hit rate) by opening a substantial, previously under-mined vein: benchmarks and empirical studies specifically evaluating the functional correctness of LLM-generated quantum code (distinct from the smaller LLM/Copilot-code-generation cluster captured in round 11 - this round found the benchmark ecosystem, including Qiskit HumanEval, the QCoder benchmark, QuanBench+ as an extension of the already-included Quanbench, an adaptation of Microsoft's QuantumKatas for LLM evaluation, an updated empirical evaluation of domain-knowledge placement in Qiskit code generation, and a study of API drift in LLM-generated code across successive SDK versions, had grown substantially since that round and was not yet reflected in the corpus). Also added three noise-aware oracle/fidelity-verification papers (Autofid's adaptive fidelity measurement, a noise-model-quality validation study, and an oracle-verification-under-noise technique) that extend the noise-aware-testing vein (round 8) with contributions not yet captured. The circuit-cutting/distributed-computing query confirmed the existing scope boundary decisively: all 9 non-duplicate hits (Cut&Shoot, DistributedEstimator, several circuit-cutting optimization theses and papers) were excluded as the already-documented compiler-optimization subfield rather than testing methodology. Also excluded: a quantum-software-size-measurement SLR (Hacaloglu et al., a metrics/sizing topic distinct from testing), a quantum-optimization-for-SE survey (Zhang et al., the survey-form counterpart of the quantum-optimization-for-classical-SE confound already documented), MQT Bench (a widely-cited compiler/design-automation benchmark rather than a testing-methodology contribution), a BB84-specific hardware paper (QKD confound), a QAOA noise-resilience preprint and a quantum-kernel anomaly-detection paper (algorithm-performance/ML-application papers, not testing).
A54: 28 | B54: 7 | C54: Round 28 (a final short pass: quantum-compiler-differential-testing-2026, property-based-testing/QuickCheck-lineage, symbolic-execution/path-coverage, and testing-practices/observability queries) closed the corpus out at exactly the user's fourth requested target, 300 rows, adding 2 rows against 7 exclusions. The differential-testing and symbolic-execution/coverage queries returned zero new rows - every hit, including Quantum concolic testing, Quantum symbolic execution, and the probabilistic condition/decision/path-coverage paper, was already in the corpus, confirming those veins are now exhaustively saturated. New rows: the original 2020 foundational paper introducing property-based testing for quantum programs in Q# (Honarvar, Mousavi & Nagarajan, 124 citations - the precursor to the QuCheck/QSharpCheck/delta-debugging cluster already in the corpus, missed by earlier rounds' more tool-focused queries), and a multivocal literature review specifically on quantum software testing spanning academic and grey literature (Gil-Pereira, Santos, de Souza Santos et al.). Exclusions confirmed the quantum-annealing-for-classical-test-suite-optimization confound in a new instance (Trovato et al.'s regression-test-suite-reformulation paper), the quantum-property-testing/complexity-theory false-friend (Montanaro & De Wolf's survey, a different subfield despite the name overlap with software property-based testing), a redundant PhD-thesis compilation (Pontolillo's thesis, whose content is already covered by the constituent QuCheck and delta-debugging papers), and two classical (non-quantum), pre-2015 software-testing papers returned by generic query terms.
A55: Running total (from Round 7) | B55: =SUM(B35:B54) -> 326
A59: Method & caveats
A60: • Corpus assembled by Google Scholar search (2015-2026) across twenty-eight rounds: (1) the OR-heavy query paged through 7 pages; (2) five Table 4 concept-group queries; (3) differential-testing, property-based-testing, EMI and Qiskit-transpiler-bug queries; (4) two more Qiskit-transpiler-bug pages plus translation-validation and LLM-based-testing queries; (5) two further Qiskit-transpiler-bug pages; (6) Cirq/tket, qubit-routing/mapping, CI-regression, and static-analysis queries; (7) quantum-testing survey/SLR, assertion-based testing, coverage-criteria/test-generation, and flaky-test queries; (8) automated program repair, symbolic execution, noise-aware/hardware-discrepancy testing, test-smell, and other-framework (PennyLane/Braket) compiler-bug queries; (9) circuit-synthesis correctness/verification, formal-specification-language (Qafny-family), optimization-level differential testing, empirical test-coverage-in-the-wild, and program-slicing/fault-localization queries. LLM-guided testing/fuzzing is an emerging technique family outside the pre-declared Table 10 taxonomy; the protocol document carries a short note on how such studies are handled at extraction (mapped to C1-C8 with an LLM-guided modifier, not a ninth family). Rounds 9-12: (9) circuit-synthesis correctness/verification, formal-specification-language (Qafny-family), optimization-level differential testing, empirical test-coverage-in-the-wild, and program-slicing/fault-localization queries; (10) metamorphic Shor/Grover, VQE/QAOA testing, test-case prioritisation, error-mitigation testing, runtime verification, test-oracle generation, search-based/genetic test generation, unit-testing frameworks, CI-adoption studies, and design-by-contract queries; (11) ZX-calculus and tensor-decision-diagram equivalence checking, LLM/Copilot quantum-code-generation correctness, qubit-allocation compiler algorithms, and GitHub-issue transpiler-bug mining; (12) Clifford/stabilizer circuit verification, compiler rewrite-rule correctness, and a second page of the round-9 circuit-synthesis query. Rounds 13-17: (13) fault injection/dynamic testing, test-suite reduction (non-confound), cross-version regression saturation check, SDK fuzzing saturation check, and QEC decoder testing/verification queries; (14) QKD/quantum-cryptography testing, mock/test-double backends, comparative tool-evaluation surveys, pytket/tket-specific, and TDD-practices queries (the QKD and TDD-practices angles returned almost entirely out-of-scope or false-positive hits); (15) model-based testing/FSM, type systems for no-cloning correctness, quantum Hoare/separation logic, white-box structural coverage, and Q#-specific bug-study queries — opening a substantial new formal-verification (Hoare/separation logic) vein; (16) weakest-precondition calculus and bisimulation/process-calculus queries; (17) a second page of the Hoare/separation-logic search. Rounds 18-21: (18) circuit cutting/knitting correctness, OpenQASM parser correctness, RL test generation, technical-debt/maintainability empirical, and resource-estimation correctness queries (finding circuit-cutting, RL-for-quantum, and lattice-surgery resource-estimation to be predominantly compiler-optimization subfields rather than testing subfields); (19) quantum-state-tomography test oracles, universal-gate-set decomposition correctness, developer survey/interviews, and cloud CI/DevOps queries (finding tomography to be predominantly a complexity-theory/physics topic); (20-21) transpilation-idempotence, flaky-test root-cause taxonomy, D-Wave annealer compilation, SMT-solver test generation, a no-cloning follow-up page, and a mutation-operator deep dive, closing out at the user's third requested target (22) bug-prediction/defect, API-misuse/compatibility, hardware-specific superconducting/trapped-ion, PennyLane automatic-differentiation, and Grover-oracle test-generation queries, the lowest-yield round to date (2 new rows against 31 exclusions), confirming the corpus is approaching saturation and surfacing two further confound-direction patterns: quantum/QML techniques used to predict defects in classical software, and Grover's algorithm applied to classical test-pattern generation/dynamic testing. Rounds 23-24 recovered a better yield (6 new rows against 17 exclusions, ~26%, after a duplicate catch removed a Qecv-framework row already present from an earlier round) Round 25 added 5 more rows against 21 exclusions (~19%) via a debugging-specific survey, a hybrid quantum-classical fault taxonomy, and three mutation-testing extensions (noise-aware, QML-model-specific, and mutation-based fault localization), while confirming that debugging-tool-comparison and mutation-testing-effectiveness angles are now almost fully saturated (nearly every hit was a duplicate) and that quantum-language-parser/frontend correctness and variational-quantum-circuit test-generation queries are dominated by programming-language-design and ansatz-design papers respectively, not testing methodology. Round 26 hit the highest duplicate rate to date (5 new rows out of roughly 45 hits across transpiler-regression, LLM-repair, general-testing-empirical, cross-platform differential-testing, and equivalence-checking-scalability queries), confirming near-total saturation of those veins, with new rows limited to an LLM-repair-plus-mutation-analysis paper and a small equivalence-checking-scalability cluster (a shallow-circuit method, its companion tool Manjushri, and a matrix-product-operator technique) plus a practitioner study on output-validation adequacy. Round 27 recovered the best yield since round 11 (9 new rows against 16 exclusions, ~36%) by opening an under-mined LLM-generated-quantum-code-correctness-evaluation benchmark ecosystem (Qiskit HumanEval, QCoder, QuanBench+, an LLM-adapted QuantumKatas, and others) and three noise-aware oracle/fidelity-verification papers, while confirming the circuit-cutting/distributed-computing angle remains firmly a compiler-optimization subfield (all 9 non-duplicate hits excluded). Round 28, a final short pass, closed the corpus out at exactly 300 rows with 2 rows against 7 exclusions: the 2020 foundational paper on property-based testing of quantum programs in Q# (Honarvar, Mousavi & Nagarajan, missed by earlier tool-focused queries despite being the precursor to the QuCheck/QSharpCheck cluster already in the corpus), and a multivocal literature review specifically on quantum software testing. The differential-testing and symbolic-execution/coverage angles returned zero new rows in this round, confirming exhaustive saturation. via QEC-specific formal-verification queries (symbolic execution, fault-tolerance verification, Qecv, ZX-calculus-based QEC verification), statistical-test-oracle refinements (mixed-state test preparation, unit-testing feasibility), simulator numerical-correctness (rounding-error bounds, Bugs4Q dataset reproducibility), and a Stack-Exchange/GitHub-issue-mining developer-challenges study, while confirming heavy saturation of the crash-bug, OpenQASM/QIR, and issue-tracker angles (nearly all hits were duplicates of already-included papers) and surfacing a new confound (adversarial-robustness/security evaluation of quantum ML models, a distinct ML-security subfield).
A61: • All hits screened for on-topic relevance to quantum-compiler/transpiler testing using the same criteria as Table 5 (Inclusion/Exclusion) of the protocol; near-duplicate tool/venue pairs (e.g. companion tool-demo papers already covered by a journal case study already in this corpus) were not re-added.
A62: • The regression/test-selection query surfaced mostly quantum-annealing-for-classical-test-selection papers, which the protocol's Table 6 confound exclusion rules out as out-of-scope (quantum optimisation applied to classical testing, not testing of the quantum compiler); these were screened and excluded, not added as rows.
A63: • 'Publisher / Index' is the primary indexing source; ICSE/ASE proceedings are co-listed in both IEEE Xplore and ACM DL (noted per row). 'Other' covers institutional repositories (HAL, Aaltodoc) and non-Western-indexed journals (dbpia.co.kr) not covered by the six main buckets.
A64: • This is a focused scoping corpus, not the full systematic-search corpus, which will come from the Table 5 database queries. It has grown across twenty-eight rounds (see the corpus-assembly note above for what each round covered); round 6 added a distinct static-analysis/bug-pattern vein (QChecker, LintQ, bug-pattern taxonomy), round 7 added assertion-based runtime testing/debugging and flaky-test detection specific to quantum software, round 8 added automated quantum program repair, symbolic execution, and test-smell detection/empirical studies, round 9 added formal-verification-of-compiler-correctness papers (Qafny family) and a fault-localization/debugging-tool cluster, round 10 added test-oracle-generation, search-based/genetic test generation, unit-testing-framework, and design-by-contract clusters (also confirming that VQE/QAOA 'testing' and quantum-annealing test-case-prioritisation queries mostly probe out-of-scope physics/confound literatures), round 11 added a substantial equivalence-checking vein (ZX-calculus and tensor-decision-diagrams, 13 papers) and an LLM/Copilot quantum-code-generation-correctness cluster, round 12 added Clifford/stabilizer circuit verification and further compiler rewrite-rule-correctness papers (reaching the user's first requested target, 200 rows, at 201), rounds 13-14 mostly confirmed saturation of several earlier veins (Qiskit-version regression, general fuzzing) and mapped out clear scope boundaries excluding QKD/quantum-cryptography and classical TDD-practices literature, while still adding fault-injection/QEC-testing, non-confound test-suite-reduction, and mock-backend/comparative-tool clusters, and rounds 15-17 opened a large, previously-untapped formal-verification vein spanning quantum Hoare logic, separation logic, weakest-precondition/refinement calculus, type systems for no-cloning correctness, and model-based testing (roughly 30 papers), including several highly-cited foundational works (Liu et al. 2019 CAV, Unruh 2019 POPL, Zhou et al. 2019 PLDI). reaching the user's second requested target, 240 rows, at 245. Rounds 18-21 added circuit-cutting correctness, OpenQASM/QASM-parser correctness, RL-based Qiskit-code-generation reliability, quantum-specific technical-debt empirical studies, SMT-solver-based verification (Silq, AutoQ 2.0), additional mutation-testing operators/tools, and two independent practitioner-survey papers, while mapping several more scope boundaries: circuit-cutting, RL-for-compiler-optimization, lattice-surgery resource-estimation, quantum-state-tomography, and D-Wave-annealer-compilation are each predominantly adjacent subfields (compiler optimization, complexity theory, or hardware) rather than software-testing subfields, and returned few or no new papers despite plausible-sounding queries. The corpus reached the user's third requested target, 270 rows, at 271 rows. Round 22 (bug-prediction/defect, API-misuse, hardware-specific superconducting/trapped-ion, PennyLane automatic-differentiation, and Grover-oracle test-generation queries) was the lowest-yield round to date, adding only 2 rows (a bug-fix empirical study and a bug-analysis thesis) against 31 exclusions, and mapped two more scope boundaries: quantum/QML techniques used to predict defects in classical software, and Grover's algorithm applied to classical test-pattern generation, are adjacent confound literatures rather than quantum-software-testing contributions. The corpus stood at 273 rows toward the user's fourth requested target, 300 rows, after round 22. Rounds 23-24 recovered a stronger yield, adding 6 rows against 17 exclusions by targeting QEC-specific formal verification (ZX-calculus-based QEC verification, extending the existing symbolic-execution/fault-tolerance-verification cluster), statistical-test-oracle refinements (mixed-state test preparation, unit-testing feasibility), simulator numerical-correctness (rounding-error bounds, Bugs4Q dataset reproducibility), and a Stack-Exchange/GitHub-issue-mining developer-challenges study, while confirming near-total saturation of the crash-bug, OpenQASM/QIR, and issue-tracker-mining angles (nearly all hits duplicated papers already in the corpus, including a Qecv-framework candidate initially added then caught and removed as a duplicate of row 209 during post-append verification) and surfacing a new scope boundary: adversarial-robustness/security evaluation of quantum machine learning models is a distinct ML-security subfield, not a software-testing-methodology contribution. The corpus stood at 279 rows toward the user's fourth requested target, 300 rows, after rounds 23-24. Round 25 added 5 more rows (a debugging-focused survey, a hybrid quantum-classical fault taxonomy, and three mutation-testing extensions covering noise, QML models, and fault localization) against 21 exclusions, while confirming the debugging-tool-comparison and mutation-testing-effectiveness angles are now almost fully saturated and mapping two more scope boundaries: quantum-language-parser/frontend correctness is dominated by programming-language-design contributions rather than testing methodology, and variational-quantum-circuit test-generation queries mostly surface ansatz-design/algorithm-performance papers, an adjacent confound similar to the existing VQE/QAOA-testing exclusion. The corpus stood at 284 rows toward the 300-row target after round 25. Round 26 hit the highest duplicate rate of any round to date - only 5 new rows out of roughly 45 hits across the transpiler-drift/regression, LLM-repair, general-testing-empirical, cross-platform differential-testing, and equivalence-checking-scalability queries, with nearly every well-known tool or paper in those spaces (QDiff, QSPE, QuaSi, QEMI, QuteFuzz, EriQua, MorphQ/MorphQ++, IterTestQ, Hornbro, the ChatGPT-repair paper, Transpilation Drift, the QBench dataset paper, and the core ZX-calculus/Clifford/model-counting equivalence-checking cluster) already captured in earlier rounds. New rows were limited to an LLM-repair-plus-mutation-analysis paper, a small equivalence-checking-scalability cluster (a shallow-circuit method and its companion tool Manjushri, plus a matrix-product-operator technique), and a practitioner study on output-validation adequacy for differential testing. The corpus stood at 289 rows toward the 300-row target after round 26. Round 27 recovered the best yield since round 11, adding 9 rows against 16 exclusions by opening a substantial, previously under-mined vein of benchmarks and empirical studies evaluating LLM-generated quantum code correctness (Qiskit HumanEval, QCoder, QuanBench+, an LLM-adapted QuantumKatas, an updated domain-knowledge-placement study, and an API-drift study), plus three noise-aware oracle/fidelity-verification papers extending the round-8 noise-aware-testing vein, while confirming that circuit-cutting/distributed quantum computing remains a compiler-optimization subfield rather than a testing-methodology one (all 9 non-duplicate hits from that query excluded). The corpus stood at 298 rows toward the 300-row target after round 27. A final short round 28 closed the gap exactly: the foundational 2020 paper on property-based testing of quantum programs in Q# (Honarvar, Mousavi & Nagarajan - the precursor to the QuCheck/QSharpCheck/delta-debugging cluster already in the corpus, missed by earlier tool-focused queries) and a multivocal literature review specifically on quantum software testing, against 7 exclusions confirming the differential-testing and symbolic-execution/coverage veins are now exhaustively saturated. The corpus reached the user's fourth requested target, 300 rows, exactly at 300 rows.
A65: • 'Maybe' rows are borderline (e.g., algorithmic-oracle compilation, evaluation infrastructure, technique applied to a non-compiler target) pending full-text screening.
A66: • Counts are live COUNTIF formulas; add rows to Corpus and re-open to refresh the tallies.
